slidetextbridge/__init__.py
slidetextbridge/core/__init__.py
slidetextbridge/core/config.py
slidetextbridge/core/configtop.py
slidetextbridge/core/context.py
slidetextbridge/core/logging.py
slidetextbridge/core/main.py
slidetextbridge/plugins/__init__.py
slidetextbridge/plugins/accumulate.py
slidetextbridge/plugins/base.py
slidetextbridge/plugins/debug_helper.py
slidetextbridge/plugins/impress.py
slidetextbridge/plugins/jmespath_filter.py
slidetextbridge/plugins/obsws.py
slidetextbridge/plugins/openlp.py
slidetextbridge/plugins/powerpoint.py
slidetextbridge/plugins/text_filters.py
slidetextbridge/plugins/webserver.py
slidetextbridge/plugins/data/webserver/default/index.html
slidetextbridge/plugins/data/webserver/default/script.js
slidetextbridge/plugins/data/webserver/default/style.css
slidetextbridge-0.3.0.dist-info/licenses/LICENSE
slidetextbridge-0.3.0.dist-info/METADATA
slidetextbridge-0.3.0.dist-info/WHEEL
slidetextbridge-0.3.0.dist-info/entry_points.txt
slidetextbridge-0.3.0.dist-info/top_level.txt
slidetextbridge-0.3.0.dist-info/RECORD
