Metadata-Version: 2.4
Name: slidetextbridge
Version: 0.3.0
Summary: Live Text Bridge from Presentation
Home-page: https://github.com/norihiro/slidetextbridge
Classifier: Development Status :: 4 - Beta
Classifier: Programming Language :: Python :: 3
Classifier: License :: OSI Approved :: MIT License
Classifier: Operating System :: OS Independent
Classifier: Intended Audience :: End Users/Desktop
Classifier: Environment :: Console
Requires-Python: >=3.9
License-File: LICENSE
Requires-Dist: pywin32; platform_system == "Windows"
Requires-Dist: pyyaml
Requires-Dist: jmespath
Requires-Dist: simpleobsws
Requires-Dist: aiohttp
Dynamic: classifier
Dynamic: description
Dynamic: description-content-type
Dynamic: home-page
Dynamic: license-file
Dynamic: requires-dist
Dynamic: requires-python
Dynamic: summary
